grafana_foundation_sdk/__init__.py
grafana_foundation_sdk/py.typed
grafana_foundation_sdk/builders/__init__.py
grafana_foundation_sdk/builders/accesspolicy.py
grafana_foundation_sdk/builders/alertgroups.py
grafana_foundation_sdk/builders/alerting.py
grafana_foundation_sdk/builders/annotationslist.py
grafana_foundation_sdk/builders/athena.py
grafana_foundation_sdk/builders/azuremonitor.py
grafana_foundation_sdk/builders/barchart.py
grafana_foundation_sdk/builders/bargauge.py
grafana_foundation_sdk/builders/bigquery.py
grafana_foundation_sdk/builders/candlestick.py
grafana_foundation_sdk/builders/canvas.py
grafana_foundation_sdk/builders/cloudwatch.py
grafana_foundation_sdk/builders/common.py
grafana_foundation_sdk/builders/dashboard.py
grafana_foundation_sdk/builders/dashboardlist.py
grafana_foundation_sdk/builders/datagrid.py
grafana_foundation_sdk/builders/datasource.py
grafana_foundation_sdk/builders/debug.py
grafana_foundation_sdk/builders/elasticsearch.py
grafana_foundation_sdk/builders/expr.py
grafana_foundation_sdk/builders/folder.py
grafana_foundation_sdk/builders/gauge.py
grafana_foundation_sdk/builders/geomap.py
grafana_foundation_sdk/builders/googlecloudmonitoring.py
grafana_foundation_sdk/builders/grafanapyroscope.py
grafana_foundation_sdk/builders/heatmap.py
grafana_foundation_sdk/builders/histogram.py
grafana_foundation_sdk/builders/librarypanel.py
grafana_foundation_sdk/builders/logs.py
grafana_foundation_sdk/builders/loki.py
grafana_foundation_sdk/builders/news.py
grafana_foundation_sdk/builders/nodegraph.py
grafana_foundation_sdk/builders/parca.py
grafana_foundation_sdk/builders/piechart.py
grafana_foundation_sdk/builders/playlist.py
grafana_foundation_sdk/builders/preferences.py
grafana_foundation_sdk/builders/prometheus.py
grafana_foundation_sdk/builders/publicdashboard.py
grafana_foundation_sdk/builders/resource.py
grafana_foundation_sdk/builders/role.py
grafana_foundation_sdk/builders/rolebinding.py
grafana_foundation_sdk/builders/stat.py
grafana_foundation_sdk-1769699998!10.1.0.dist-info/METADATA
grafana_foundation_sdk-1769699998!10.1.0.dist-info/WHEEL
grafana_foundation_sdk-1769699998!10.1.0.dist-info/licenses/LICENSE
grafana_foundation_sdk-1769699998!10.1.0.dist-info/RECORD
