Metadata-Version: 2.4
Name: grafana_foundation_sdk
Version: 1769699998!10.1.0
Summary: A set of tools, types and libraries for building and manipulating Grafana objects.
Project-URL: Homepage, https://github.com/grafana/grafana-foundation-sdk
Project-URL: Repository, https://github.com/grafana/grafana-foundation-sdk.git
Project-URL: Issues, https://github.com/grafana/grafana-foundation-sdk/issues
Author: Grafana Labs
License-File: LICENSE
Keywords: grafana,logs,metrics,observability,sdk,traces
Classifier: Development Status :: 3 - Alpha
Classifier: Intended Audience :: Developers
Classifier: Intended Audience :: System Administrators
Classifier: License :: OSI Approved :: Apache Software License
Classifier: Operating System :: OS Independent
Classifier: Programming Language :: Python :: 3.11
Classifier: Programming Language :: Python :: 3.12
Classifier: Topic :: Software Development :: Libraries
Classifier: Topic :: System :: Monitoring
Requires-Python: >=3.11
